[{"tweet":{"date":"2020-25-19 01:25:11","user":"BrixInvest","content":"#LEGO #LEGOStarWars #StarWars set 7964 - Republic Figate?, 2011 Release #TheCloneWars #Yoda #LEGOVehicles #AFOL #LEGObricks  #CollectibleToys #SP500 #stocks  #legoresaleprices  #LEGOblocks https:\/\/t.co\/DgRD98B3tO"}},{"tweet":{"date":"2020-25-19 01:25:10","user":"juana_weiser","content":"These are the 5 biggest bombshells from The New York Times' report on Trump's money and Deutsche Bank | Markets Insider https:\/\/t.co\/jLhZ0SrtkK"}},{"tweet":{"date":"2020-25-19 01:25:10","user":"Brian83353294","content":"@PramilaJayapal @BernieSanders Flip it into a socialist government run utopia of crying entitled brats.   Bernie will destroy our economy.  Day one the stocks will drop to record lows. Save this tweet... you know I'm right"}},{"tweet":{"date":"2020-25-19 01:25:04","user":"fxnewstodayAE","content":"???? ?????? ??????? ? ????????? (MADAR) ?????? ?????? ?????? -????? ?????- 19-02-2020: ???? ????? ?? ???????? ??? ???? ???  ????? ?? ???????? ??????? ??? ????? ??? ?????? ??????? ... https:\/\/t.co\/AqqBwxYohl"}},{"tweet":{"date":"2020-25-19 01:25:04","user":"RTTNews","content":"Sensex Up Over 200 Points In Early Trade; Nifty At 12062 https:\/\/t.co\/1ENnAsRnEN #stocks #trading #rttnews https:\/\/t.co\/GJ8UU3dB75"}},{"tweet":{"date":"2020-25-19 01:25:03","user":"fxnewstodayAE","content":"???? ??? ?????? ??????? ??????? (FIRSTDUBAI) ???? ?????? -????? ?????- 19-02-2020: ???? ????? ??????? ??? ???????? ?????? ??? ????? 47?50 ???? ???? ????? ???? ????? ?????? ??? ????? ... https:\/\/t.co\/xfI8QvJLYe"}},{"tweet":{"date":"2020-25-19 01:25:03","user":"fxnewstodayAE","content":"?????? ?????????? ??????? (INVESTORS) ???? ??? ??????? -????? ?????- 19-02-2020: ????? ????? ????? ???? ??? ???????? ??? ???? ??? ???????? ??? ????? 12?30 ???? ?? ?? ???? ????? ... https:\/\/t.co\/THfB5AV0QE"}},{"tweet":{"date":"2020-25-19 01:25:03","user":"fxnewstodayAE","content":"????? ??????? ???? ?????? ?? ?????? \u2013 ????? ????? \u2013 19-02-2020: ??? ????? ??? ????? ??????? (7020) ????? ??? ?? ?? ??? ?????? ??? 23.42? ?????? ???? ??? ??? ?? ... https:\/\/t.co\/rwGiCMvRhF"}},{"tweet":{"date":"2020-25-19 01:25:02","user":"fxnewstodayAE","content":"?????? ??????? ??????? (UDCD) ???? ?????? -????? ?????- 19-02-2020: ??? ????? ??????? ???? ???? ???????? ??????? ??? ???? ??? ????? 1?216 ????? ????? ???? ?????? ???? ... https:\/\/t.co\/1y4C4ISsHS"}},{"tweet":{"date":"2020-24-19 01:24:59","user":"riamariiaaa","content":"@geexii26fanacc hi, a friend of mine saw this. you might want to try asking them if they still have stocks. https:\/\/t.co\/Fta0HB3S0R"}},{"tweet":{"date":"2020-24-19 01:24:45","user":"Nadu108","content":"MOST HOPELESS STOCKS OF THE LAST YEAR......"}},{"tweet":{"date":"2020-25-19 01:25:11","user":"BrixInvest","content":"#LEGO #LEGOStarWars #StarWars set 7964 - Republic Figate?, 2011 Release #TheCloneWars #Yoda #LEGOVehicles #AFOL #LEGObricks  #CollectibleToys #SP500 #stocks  #legoresaleprices  #LEGOblocks https:\/\/t.co\/DgRD98B3tO"}},{"tweet":{"date":"2020-25-19 01:25:10","user":"juana_weiser","content":"These are the 5 biggest bombshells from The New York Times' report on Trump's money and Deutsche Bank | Markets Insider https:\/\/t.co\/jLhZ0SrtkK"}},{"tweet":{"date":"2020-25-19 01:25:10","user":"Brian83353294","content":"@PramilaJayapal @BernieSanders Flip it into a socialist government run utopia of crying entitled brats.   Bernie will destroy our economy.  Day one the stocks will drop to record lows. Save this tweet... you know I'm right"}},{"tweet":{"date":"2020-25-19 01:25:04","user":"fxnewstodayAE","content":"???? ?????? ??????? ? ????????? (MADAR) ?????? ?????? ?????? -????? ?????- 19-02-2020: ???? ????? ?? ???????? ??? ???? ???  ????? ?? ???????? ??????? ??? ????? ??? ?????? ??????? ... https:\/\/t.co\/AqqBwxYohl"}},{"tweet":{"date":"2020-25-19 01:25:04","user":"RTTNews","content":"Sensex Up Over 200 Points In Early Trade; Nifty At 12062 https:\/\/t.co\/1ENnAsRnEN #stocks #trading #rttnews https:\/\/t.co\/GJ8UU3dB75"}},{"tweet":{"date":"2020-25-19 01:25:03","user":"fxnewstodayAE","content":"???? ??? ?????? ??????? ??????? (FIRSTDUBAI) ???? ?????? -????? ?????- 19-02-2020: ???? ????? ??????? ??? ???????? ?????? ??? ????? 47?50 ???? ???? ????? ???? ????? ?????? ??? ????? ... https:\/\/t.co\/xfI8QvJLYe"}},{"tweet":{"date":"2020-25-19 01:25:03","user":"fxnewstodayAE","content":"?????? ?????????? ??????? (INVESTORS) ???? ??? ??????? -????? ?????- 19-02-2020: ????? ????? ????? ???? ??? ???????? ??? ???? ??? ???????? ??? ????? 12?30 ???? ?? ?? ???? ????? ... https:\/\/t.co\/THfB5AV0QE"}},{"tweet":{"date":"2020-25-19 01:25:03","user":"fxnewstodayAE","content":"????? ??????? ???? ?????? ?? ?????? \u2013 ????? ????? \u2013 19-02-2020: ??? ????? ??? ????? ??????? (7020) ????? ??? ?? ?? ??? ?????? ??? 23.42? ?????? ???? ??? ??? ?? ... https:\/\/t.co\/rwGiCMvRhF"}},{"tweet":{"date":"2020-25-19 01:25:02","user":"fxnewstodayAE","content":"?????? ??????? ??????? (UDCD) ???? ?????? -????? ?????- 19-02-2020: ??? ????? ??????? ???? ???? ???????? ??????? ??? ???? ??? ????? 1?216 ????? ????? ???? ?????? ???? ... https:\/\/t.co\/1y4C4ISsHS"}},{"tweet":{"date":"2020-24-19 01:24:59","user":"riamariiaaa","content":"@geexii26fanacc hi, a friend of mine saw this. you might want to try asking them if they still have stocks. https:\/\/t.co\/Fta0HB3S0R"}},{"tweet":{"date":"2020-24-19 01:24:45","user":"Nadu108","content":"MOST HOPELESS STOCKS OF THE LAST YEAR......"}}]